[
  {
    "title": "Open TechCall",
    "color": "#dab82d",
    "rrule": {
      "freq": "monthly",
      "dtstart": "2024-10-23T14:00:00",
      "bysetpos": 4,
      "interval": 1,
      "byweekday": 5,
      "tzid": "Europe/Berlin"
    },
    "exdate": [
      "2024-12-23T14:00:00"
    ]
  },
  {
    "title": "OCR-D in der Praxis",
    "color": "#b8da2d",
    "rrule": {
      "freq": "weekly",
      "interval": 2,
      "dtstart": "2024-11-08T13:00:00",
      "tzid": "Europe/Berlin"
    },
    "exdate": [
      "2025-01-03T13:00:00",
      "2024-11-22T13:00:00"
    ]
  }
]
